CustomizeProxy/__init__.py
CustomizeProxy/proxy.py
CustomizeProxy-0.0.1.dist-info/LICENSE
CustomizeProxy-0.0.1.dist-info/METADATA
CustomizeProxy-0.0.1.dist-info/WHEEL
CustomizeProxy-0.0.1.dist-info/top_level.txt
CustomizeProxy-0.0.1.dist-info/RECORD
