Metadata-Version: 2.1
Name: CustomizeProxy
Version: 0.0.1
Summary: 这是一个 mitmproxy 二次封装版本
Home-page: https://github.com/mitmproxy/mitmproxy/
Author: CC
Author-email: 3204604858@qq.com
License: MIT License
Keywords: CustomizeProxy
Platform: Windows
Classifier: Intended Audience :: Developers
Classifier: Programming Language :: Python :: 3.10
Classifier: Programming Language :: Python :: 3.11
Classifier: Programming Language :: Python :: 3.12
Classifier: Topic :: Software Development :: Libraries
Classifier: Topic :: Software Development :: Libraries :: Python Modules
Classifier: Topic :: Software Development :: User Interfaces
Requires-Python: >=3.10
License-File: LICENSE
Requires-Dist: mitmproxy
